README.md
setup.py
services_communication/__init__.py
services_communication/apps.py
services_communication/broker.py
services_communication/error.py
services_communication/logging.py
services_communication/models.py
services_communication/settings.py
services_communication/utils.py
services_communication.egg-info/PKG-INFO
services_communication.egg-info/SOURCES.txt
services_communication.egg-info/dependency_links.txt
services_communication.egg-info/requires.txt
services_communication.egg-info/top_level.txt
services_communication/call/__init__.py
services_communication/call/command.py
services_communication/consumer/__init__.py
services_communication/consumer/process.py
services_communication/management/__init__.py
services_communication/management/commands/__init__.py
services_communication/management/commands/devconsumer.py
services_communication/management/commands/devpublisher.py
services_communication/management/commands/runconsumer.py
services_communication/management/commands/runpublisher.py
services_communication/migrations/0001_initial.py
services_communication/migrations/__init__.py
services_communication/publisher/__init__.py
services_communication/publisher/process.py
services_communication/publisher/utils.py
services_communication/rest_api/__init__.py
services_communication/rest_api/auth_helper.py
services_communication/rest_api/client_api_helper.py
services_communication/rest_api/error.py
services_communication/rest_api/formatter.py
services_communication/rest_api/utils.py