Metadata-Version: 2.1
Name: services-communication
Version: 2.1.2
Summary: Pub/Sub for microservice on django
Home-page: https://github.com/ksinn/django-microservices-communication
Author: ksinn
Author-email: ksinnd@gmail.com
